mindhive/__init__.py
mindhive/dalsa/__init__.py
mindhive/dalsa/dalsa_api.py
mindhive/dalsa/dalsa_c_data.py
mindhive/dalsa/dalsa_calibration_image.py
mindhive/dalsa/dalsa_camera_array.py
mindhive/dalsa/dalsa_camera_array_strip_producer.py
mindhive/dalsa/dalsa_camera_producer.py
mindhive/dalsa/dalsa_error.py
mindhive/dalsa/dalsa_frame_buffer.py
mindhive/dalsa/dalsa_px_format.py
mindhive/dalsa/install/__init__.py
mindhive/dalsa/install/__main__.py
mindhive/dalsa/install/cpp/dalsa.cpp
mindhive/debug/__init__.py
mindhive/debug/external_output.py
mindhive/debug/pydevd-pycharm.egg
mindhive/debug/remote_debugging.py
mindhive/errors/__init__.py
mindhive/errors/fatal_exception.py
mindhive/fixture/__init__.py
mindhive/fixture/matchers.py
mindhive/fixture/mock_event.py
mindhive/fixture/mock_processor.py
mindhive/fixture/mock_queue.py
mindhive/fixture/mock_redis_listener.py
mindhive/fixture/mock_time.py
mindhive/fixture/some.py
mindhive/fixture/some_image.py
mindhive/fixture/strip_matchers.py
mindhive/fixture/thread.py
mindhive/fixture/worker.py
mindhive/frame/__init__.py
mindhive/frame/frame.py
mindhive/frame/frame_array_strip_composer.py
mindhive/frame/frame_height.py
mindhive/frame/load_frames_producer.py
mindhive/frame/single_frame_strip_transformer.py
mindhive/gev/__init__.py
mindhive/gev/cam_error.py
mindhive/gev/camera_array_config.py
mindhive/gev/camera_network.py
mindhive/gev/frame_id_tracking.py
mindhive/gev/mock_camera_array.py
mindhive/gev/px_format.py
mindhive/gev/px_layout.py
mindhive/hik/__init__.py
mindhive/hik/encoder_worker.py
mindhive/hik/hik_api.py
mindhive/hik/hik_c_data.py
mindhive/hik/hik_calibration_image.py
mindhive/hik/hik_camera_array.py
mindhive/hik/hik_camera_array_strip_producer.py
mindhive/hik/hik_camera_producer.py
mindhive/hik/hik_error.py
mindhive/hik/hik_frame.py
mindhive/hik/hik_px_format.py
mindhive/hik/install/__main__.py
mindhive/hik/install/cpp/hik.cpp
mindhive/hik/install/include/CameraParams.h
mindhive-3.3.0.dist-info/METADATA
mindhive-3.3.0.dist-info/WHEEL
mindhive-3.3.0.dist-info/RECORD
