Metadata-Version: 2.1
Name: mindhive
Version: 3.3.0
Summary: Mindhive standard packages
Home-page: https://github.com/mindhivenz/mindhive-packages-py.git
License: Proprietary
Author: Mindhive devs
Author-email: devops@mindhive.co.nz
Requires-Python: >=3.12,<3.13
Classifier: License :: Other/Proprietary License
Classifier: Programming Language :: Python :: 3
Classifier: Programming Language :: Python :: 3.12
Requires-Dist: datadog (>=0.49,<0.50)
Requires-Dist: datadog-api-client (>=2,<3)
Requires-Dist: datadog-log (>=1,<2)
Requires-Dist: ddtrace (>=2,<3)
Requires-Dist: numpy (>=1,<2)
Requires-Dist: opencv-python-headless (>=4,<5)
Requires-Dist: ping3 (>=4,<5)
Requires-Dist: psutil (>=6,<7)
Requires-Dist: redis (>=5,<6)
Requires-Dist: typer (>=0.12,<0.13)
Project-URL: Repository, https://github.com/mindhivenz/mindhive-packages-py.git
